{
	"abstract" : true,
	"backtrace" : 3,
	"backtraceGraph" : 
	{
		"commands" : 
		[
			"add_library",
			"pico_simple_hardware_headers_target",
			"pico_simple_hardware_target",
			"target_link_libraries",
			"pico_mirrored_target_link_libraries",
			"pico_simple_hardware_impl_target"
		],
		"files" : 
		[
			"C:/Users/zhasanr/Desktop/pico-sdk/src/CMakeLists.txt",
			"C:/Users/zhasanr/Desktop/pico-sdk/src/rp2_common/hardware_flash/CMakeLists.txt"
		],
		"nodes" : 
		[
			{
				"file" : 1
			},
			{
				"command" : 2,
				"file" : 1,
				"line" : 1,
				"parent" : 0
			},
			{
				"command" : 1,
				"file" : 0,
				"line" : 88,
				"parent" : 1
			},
			{
				"command" : 0,
				"file" : 0,
				"line" : 120,
				"parent" : 2
			},
			{
				"command" : 3,
				"file" : 0,
				"line" : 123,
				"parent" : 2
			},
			{
				"command" : 3,
				"file" : 0,
				"line" : 125,
				"parent" : 2
			},
			{
				"command" : 5,
				"file" : 0,
				"line" : 89,
				"parent" : 1
			},
			{
				"command" : 4,
				"file" : 0,
				"line" : 167,
				"parent" : 6
			},
			{
				"command" : 3,
				"file" : 0,
				"line" : 65,
				"parent" : 7
			},
			{
				"command" : 4,
				"file" : 1,
				"line" : 2,
				"parent" : 0
			},
			{
				"command" : 3,
				"file" : 0,
				"line" : 65,
				"parent" : 9
			},
			{
				"command" : 4,
				"file" : 1,
				"line" : 3,
				"parent" : 0
			},
			{
				"command" : 3,
				"file" : 0,
				"line" : 65,
				"parent" : 11
			}
		]
	},
	"codemodelVersion" : 
	{
		"major" : 2,
		"minor" : 9
	},
	"id" : "hardware_flash_headers::@49aa2da6eab3b3a59dee",
	"interfaceCompileDependencies" : 
	[
		{
			"backtrace" : 4,
			"id" : "pico_base_headers::@33789676aab31f619839"
		},
		{
			"backtrace" : 5,
			"id" : "hardware_structs::@09cfa73b2e42dc9b73b0"
		},
		{
			"backtrace" : 5,
			"id" : "hardware_claim_headers::@25444e7956dbbf3aa99e"
		},
		{
			"backtrace" : 8,
			"id" : "pico_platform_headers::@492c3b535f6fa984055f"
		},
		{
			"backtrace" : 10,
			"id" : "pico_bootrom_headers::@5b7a36be3eedb58ea3ff"
		},
		{
			"backtrace" : 12,
			"id" : "hardware_xip_cache_headers::@d89a83f4604ba86630cb"
		}
	],
	"interfaceLinkLibraries" : 
	[
		{
			"backtrace" : 4,
			"id" : "pico_base_headers::@33789676aab31f619839"
		},
		{
			"backtrace" : 5,
			"id" : "hardware_structs::@09cfa73b2e42dc9b73b0"
		},
		{
			"backtrace" : 5,
			"id" : "hardware_claim_headers::@25444e7956dbbf3aa99e"
		},
		{
			"backtrace" : 8,
			"id" : "pico_platform_headers::@492c3b535f6fa984055f"
		},
		{
			"backtrace" : 10,
			"id" : "pico_bootrom_headers::@5b7a36be3eedb58ea3ff"
		},
		{
			"backtrace" : 12,
			"id" : "hardware_xip_cache_headers::@d89a83f4604ba86630cb"
		}
	],
	"name" : "hardware_flash_headers",
	"paths" : 
	{
		"build" : "pico-sdk/src/rp2_common/hardware_flash",
		"source" : "C:/Users/zhasanr/Desktop/pico-sdk/src/rp2_common/hardware_flash"
	},
	"sources" : [],
	"type" : "INTERFACE_LIBRARY"
}
